{
  "trained_at": "2026-03-20T14:21:19.089905",
  "n_samples": 5484,
  "n_positive": 1818,
  "n_negative": 3666,
  "n_features": 42,
  "n_cv_folds": 5,
  "cv_metrics": [
    {
      "fold": 0,
      "accuracy": 0.3315,
      "precision": 0.2359,
      "recall": 0.9246,
      "f1": 0.3759,
      "auc": 0.6514,
      "logloss": 0.6685,
      "n_train": 914,
      "n_val": 914,
      "best_iter": 8
    },
    {
      "fold": 1,
      "accuracy": 0.7199,
      "precision": 0.5688,
      "recall": 0.6981,
      "f1": 0.6268,
      "auc": 0.7989,
      "logloss": 0.5135,
      "n_train": 1828,
      "n_val": 914,
      "best_iter": 189
    },
    {
      "fold": 2,
      "accuracy": 0.8446,
      "precision": 0.7391,
      "recall": 0.8041,
      "f1": 0.7702,
      "auc": 0.9018,
      "logloss": 0.3647,
      "n_train": 2742,
      "n_val": 914,
      "best_iter": 613
    },
    {
      "fold": 3,
      "accuracy": 0.8217,
      "precision": 0.5645,
      "recall": 0.5615,
      "f1": 0.563,
      "auc": 0.829,
      "logloss": 0.3848,
      "n_train": 3656,
      "n_val": 914,
      "best_iter": 305
    },
    {
      "fold": 4,
      "accuracy": 0.5383,
      "precision": 0.4536,
      "recall": 0.6133,
      "f1": 0.5215,
      "auc": 0.5697,
      "logloss": 0.6692,
      "n_train": 4570,
      "n_val": 914,
      "best_iter": 10
    }
  ],
  "avg_metrics": {
    "accuracy": 0.6512,
    "precision": 0.5124,
    "recall": 0.7203,
    "f1": 0.5715,
    "auc": 0.7502,
    "logloss": 0.5201
  },
  "feature_importance": {
    "atr_pct": 10210,
    "spy_sma200_dist": 6478,
    "vixy_relative": 4932,
    "rvol_20": 4140,
    "adx": 3312,
    "ema200_slope": 2866,
    "ema_slow_trend_ratio": 1975,
    "bb_width": 1872,
    "vol_trend": 1787,
    "stoch_d": 1401,
    "dist_ema_200": 1343,
    "ema50_slope": 1246,
    "macd_hist": 1224,
    "adx_slope_3d": 1123,
    "ret_10d": 1096,
    "stoch_k_minus_d": 1056,
    "ema_fast_slow_ratio": 1049,
    "rvol_5": 1049,
    "rsi_slope_3d": 992,
    "dist_to_resistance": 940,
    "stoch_k_slope_3d": 879,
    "rsi_delta": 772,
    "ret_3d": 768,
    "ret_20d": 743,
    "ret_5d": 715,
    "bb_pctb": 660,
    "vol_ratio_slope_3d": 630,
    "macd_hist_delta": 607,
    "vol_ratio": 596,
    "rsi": 589,
    "ret_1d": 578,
    "macd_hist_slope_3d": 562,
    "vol_delta": 541,
    "dist_to_support": 529,
    "day_of_week": 511,
    "stoch_k": 476,
    "dist_ema_slow": 417,
    "entry_score": 401,
    "dist_ema_trend": 389,
    "dist_ema_fast": 355,
    "higher_high_5": 207,
    "higher_low_5": 14
  },
  "final_n_rounds": 239,
  "params": {
    "objective": "binary",
    "metric": "binary_logloss",
    "boosting_type": "gbdt",
    "num_leaves": 57,
    "max_depth": 5,
    "learning_rate": 0.05906011860031441,
    "subsample": 0.9520031863821994,
    "colsample_bytree": 0.7707236825613936,
    "reg_alpha": 0.0026493835988486026,
    "reg_lambda": 0.014408109991314194,
    "min_child_samples": 21,
    "scale_pos_weight": 2.0165016501650164
  },
  "model_type": "inverse",
  "symbols": [
    "DOG",
    "DRV",
    "FAZ",
    "PSQ",
    "RWM",
    "SDOW",
    "SH",
    "SOXS",
    "SPXS",
    "SQQQ",
    "SRTY",
    "TZA"
  ],
  "months": 24,
  "label_params": {
    "forward_bars": 5,
    "min_gain_pct": 0.03
  },
  "recency_weighting": {
    "enabled": true,
    "halflife_days": 90,
    "min_weight": 0.1,
    "weight_min": 0.4528,
    "weight_max": 4.257
  },
  "cv_threshold": 0.4,
  "training_time_s": 157.3
}